investimentpy/__init__.py
investimentpy/core.py
investpy/__init__.py
investpy/calculos.py
investpy/dados.py
investpy/visualizacao.py
investimentpy_package-1.0.0.dist-info/METADATA
investimentpy_package-1.0.0.dist-info/WHEEL
investimentpy_package-1.0.0.dist-info/top_level.txt
investimentpy_package-1.0.0.dist-info/RECORD
