Metadata-Version: 2.4
Name: investimentpy-package
Version: 1.0.0
Summary: Descricao da sua lib investimentpy
Home-page: https://github.com/mari-oliv/investimentpy
Author: Marina Oliveira
Author-email: marina.oliveira.lw@gmail.com
License: MIT
Dynamic: author
Dynamic: author-email
Dynamic: description
Dynamic: description-content-type
Dynamic: home-page
Dynamic: license
Dynamic: summary
